mapyl/__init__.py
mapyl/test.py
mapyl/NN/__init__.py
mapyl/NN/_acc.py
mapyl/NN/_model.py
mapyl/NN/activations.py
mapyl/NN/layers.py
mapyl/NN/loss.py
mapyl/NN/optimizers.py
mapyl/classification/__init__.py
mapyl/classification/_knear.py
mapyl/classification/softmax_class.py
mapyl/classification/svm.py
mapyl/clustering/__init__.py
mapyl/clustering/_dbscan.py
mapyl/clustering/_kmeans.py
mapyl/data/_2d_data.py
mapyl/data/__init__.py
mapyl/data/_acc.py
mapyl/preprocessing/__init__.py
mapyl/preprocessing/_num.py
mapyl/preprocessing/_scale.py
mapyl/regression/__init__.py
mapyl/regression/_graddesc.py
mapyl/regression/_regression.py
mapyl/regression/logistic_regression.py
mapyl/utils/__init__.py
mapyl/utils/_numutils.py
mapyl-0.3.0.dist-info/LICENSE
mapyl-0.3.0.dist-info/METADATA
mapyl-0.3.0.dist-info/WHEEL
mapyl-0.3.0.dist-info/top_level.txt
mapyl-0.3.0.dist-info/RECORD
