Metadata-Version: 2.1
Name: mapyl
Version: 0.3.0
Summary: A Python Machine learning libary
Home-page: UNKNOWN
Author: brohgue
License: Apache License 2.0
Platform: UNKNOWN
Classifier: Intended Audience :: Developers
Classifier: License :: OSI Approved :: Apache Software License
Classifier: Programming Language :: Python
Classifier: Programming Language :: Python :: 3
Classifier: Programming Language :: Python :: 3.7
Requires: numpy
License-File: LICENSE
